swagger_client/__init__.py
swagger_client/api_client.py
swagger_client/configuration.py
swagger_client/rest.py
swagger_client/api/__init__.py
swagger_client/api/default_api.py
swagger_client/api/people_api.py
swagger_client/api/preferences_api.py
swagger_client/api/publications_api.py
swagger_client/api/sshkeys_api.py
swagger_client/models/__init__.py
swagger_client/models/author_id.py
swagger_client/models/author_id_type.py
swagger_client/models/people_long.py
swagger_client/models/people_short.py
swagger_client/models/preference_type.py
swagger_client/models/preferences.py
swagger_client/models/ssh_key_bastion.py
swagger_client/models/ssh_key_long.py
swagger_client/models/ssh_key_pair.py
swagger_client/models/ssh_key_status.py
swagger_client/models/ssh_key_type.py
swagger_client/models/version.py
test/__init__.py
test/test_author_id.py
test/test_author_id_type.py
test/test_default_api.py
test/test_people_api.py
test/test_people_long.py
test/test_people_short.py
test/test_preference_type.py
test/test_preferences.py
test/test_preferences_api.py
test/test_publications_api.py
test/test_ssh_key_bastion.py
test/test_ssh_key_long.py
test/test_ssh_key_pair.py
test/test_ssh_key_status.py
test/test_ssh_key_type.py
test/test_sshkeys_api.py
test/test_version.py
uis_swagger_client-1.1.0.dist-info/METADATA
uis_swagger_client-1.1.0.dist-info/WHEEL
uis_swagger_client-1.1.0.dist-info/top_level.txt
uis_swagger_client-1.1.0.dist-info/RECORD
